dbtr/cli/cloud_providers/arm_templates/azuredeploy.json
dbtr/cli/cloud_providers/az.py
dbtr/cli/cloud_providers/gcp.py
dbtr/cli/cloud_providers/local.py
dbtr/cli/main.py
dbtr/cli/params.py
dbtr/cli/requires.py
dbtr/cli/utils.py
dbtr/cli/version.py
dbtr/common/exceptions.py
dbtr/common/job.py
dbtr/common/project.py
dbtr/common/remote_server.py
dbtr/common/schedule.py
dbtr/server/Dockerfile
dbtr/server/config.py
dbtr/server/lib/artifacts.py
dbtr/server/lib/database.py
dbtr/server/lib/db_init.sql
dbtr/server/lib/dbt_executor.py
dbtr/server/lib/lock.py
dbtr/server/lib/logger.py
dbtr/server/lib/models.py
dbtr/server/lib/scheduler/azure.py
dbtr/server/lib/scheduler/base.py
dbtr/server/lib/scheduler/gcp.py
dbtr/server/lib/scheduler/local.py
dbtr/server/main.py
dbtr/server/requirements.txt
dbtr/server/startup.sh
dbtr/server/version.py
dbtr/ui/__init__.py
dbtr/ui/components/docs.py
dbtr/ui/components/elementary.py
dbtr/ui/components/project_selector.py
dbtr/ui/components/run_history.py
dbtr/ui/components/run_logs.py
dbtr/ui/components/schedules.py
dbtr/ui/components/tabs.py
dbtr/ui/job_with_status.py
dbtr/ui/main.py
dbtr/ui/server_utils.py
dbtr-0.3.6.dist-info/LICENSE
dbtr-0.3.6.dist-info/METADATA
dbtr-0.3.6.dist-info/WHEEL
dbtr-0.3.6.dist-info/entry_points.txt
dbtr-0.3.6.dist-info/RECORD
