Metadata-Version: 2.1
Name: dbtr
Version: 0.3.6
Summary: An extension for the dbt CLI that allows deploying and running jobs remotely
License: Apache2.0
Author: Alexis VIALARET
Author-email: alexis.vialaret@artefact.com
Requires-Python: >=3.10,<4.0
Classifier: License :: Other/Proprietary License
Classifier: Programming Language :: Python :: 3
Classifier: Programming Language :: Python :: 3.10
Classifier: Programming Language :: Python :: 3.11
Classifier: Programming Language :: Python :: 3.12
Provides-Extra: azure
Provides-Extra: google
Provides-Extra: local
Requires-Dist: ansi2html (>=1,<2)
Requires-Dist: azure-identity (>=1,<2) ; extra == "azure"
Requires-Dist: azure-mgmt-resource (>=23,<24) ; extra == "azure"
Requires-Dist: click (>=8,<9)
Requires-Dist: cron-descriptor (>=1,<2)
Requires-Dist: crontzconvert (>=0.1,<0.2)
Requires-Dist: dbt-bigquery (>=1,<2) ; extra == "google"
Requires-Dist: dbt-core (>=1,<2)
Requires-Dist: dbutils (>=3,<4)
Requires-Dist: elementary-data (>=0.15,<0.16)
Requires-Dist: extra-streamlit-components (>=0.1,<0.2)
Requires-Dist: fastapi (>=0,<1)
Requires-Dist: google-api-python-client (>=2,<3) ; extra == "google"
Requires-Dist: google-cloud-compute (>=1,<2) ; extra == "google"
Requires-Dist: google-cloud-iam (>=2,<3) ; extra == "google"
Requires-Dist: google-cloud-resource-manager (>=1,<2) ; extra == "google"
Requires-Dist: google-cloud-run (>=0,<1) ; extra == "google"
Requires-Dist: google-cloud-scheduler (>=2,<3) ; extra == "google"
Requires-Dist: google-cloud-storage (>=2,<3) ; extra == "google"
Requires-Dist: humanize (>=4,<5)
Requires-Dist: pytest (>=8,<9)
Requires-Dist: pytest-xdist (>=3,<4)
Requires-Dist: python-multipart (>=0,<1)
Requires-Dist: rich (>=13,<14)
Requires-Dist: skaff-telemetry (>=0.1,<0.2)
Requires-Dist: snowflake-id (>=1,<2)
Requires-Dist: sqlalchemy (>=2,<3)
Requires-Dist: streamlit (>=1.30,<2.0)
Requires-Dist: tzlocal (>=5,<6)
Requires-Dist: uvicorn (>=0,<1)
